Metadata-Version: 2.4
Name: llama-index-readers-guru
Version: 0.4.1
Summary: llama-index readers guru integration
Author-email: Your Name <you@example.com>
Maintainer: mcclain-thiel
License-Expression: MIT
License-File: LICENSE
Keywords: getguru,guru,knowledge base
Requires-Python: <4.0,>=3.9
Requires-Dist: bs4
Requires-Dist: llama-index-core<0.15,>=0.13.0
Requires-Dist: pandas
